setup.py
wangxin/__init__.py
wangxin.egg-info/PKG-INFO
wangxin.egg-info/SOURCES.txt
wangxin.egg-info/dependency_links.txt
wangxin.egg-info/not-zip-safe
wangxin.egg-info/top_level.txt