Metadata-Version: 1.0
Name: wangxin
Version: 0.1.0
Summary: egg test demo.
Home-page: UNKNOWN
Author: xin.wang4
Author-email: xin.wang4@ossxp.com
License: GPL
Keywords: demo,egg
Platform: Independant
